LICENSE
README.md
setup.py
act/types/__init__.py
act/types/format.py
act/types/graph_datamodel.py
act/types/types.py
act/types/etc/fact-types.json
act/types/etc/meta-fact-types.json
act/types/etc/object-types.json
act_types.egg-info/PKG-INFO
act_types.egg-info/SOURCES.txt
act_types.egg-info/dependency_links.txt
act_types.egg-info/entry_points.txt
act_types.egg-info/namespace_packages.txt
act_types.egg-info/top_level.txt
act_types.egg-info/zip-safe
test/test_format.py
test/test_validator.py